README.txt
setup.py
Products/__init__.py
Products.PloneServicesCenter.egg-info/PKG-INFO
Products.PloneServicesCenter.egg-info/SOURCES.txt
Products.PloneServicesCenter.egg-info/dependency_links.txt
Products.PloneServicesCenter.egg-info/namespace_packages.txt
Products.PloneServicesCenter.egg-info/not-zip-safe
Products.PloneServicesCenter.egg-info/requires.txt
Products.PloneServicesCenter.egg-info/top_level.txt
Products/PloneServicesCenter/__init__.py
Products/PloneServicesCenter/config.py
Products/PloneServicesCenter/configure.zcml
Products/PloneServicesCenter/interfaces.py
Products/PloneServicesCenter/testing.py
Products/PloneServicesCenter/validators.py
Products/PloneServicesCenter/browser/__init__.py
Products/PloneServicesCenter/browser/configure.zcml
Products/PloneServicesCenter/browser/providers.py
Products/PloneServicesCenter/content/Buzz.py
Products/PloneServicesCenter/content/BuzzFolder.py
Products/PloneServicesCenter/content/CaseStudy.py
Products/PloneServicesCenter/content/CaseStudyFolder.py
Products/PloneServicesCenter/content/Provider.py
Products/PloneServicesCenter/content/ProviderFolder.py
Products/PloneServicesCenter/content/Services.py
Products/PloneServicesCenter/content/ServicesFolder.py
Products/PloneServicesCenter/content/SiteUsingPlone.py
Products/PloneServicesCenter/content/SiteUsingPloneFolder.py
Products/PloneServicesCenter/content/__init__.py
Products/PloneServicesCenter/content/country.py
Products/PloneServicesCenter/i18n/ploneservicescenter-plone-es.po
Products/PloneServicesCenter/i18n/ploneservicescenter-plone.pot
Products/PloneServicesCenter/locales/ploneservicescenter-manual.pot
Products/PloneServicesCenter/locales/ploneservicescenter.pot
Products/PloneServicesCenter/locales/rebuild_i18n.sh
Products/PloneServicesCenter/locales/es/LC_MESSAGES/ploneservicescenter.po
Products/PloneServicesCenter/profiles/default/catalog.xml
Products/PloneServicesCenter/profiles/default/cssregistry.xml
Products/PloneServicesCenter/profiles/default/factorytool.xml
Products/PloneServicesCenter/profiles/default/metadata.xml
Products/PloneServicesCenter/profiles/default/propertiestool.xml
Products/PloneServicesCenter/profiles/default/skins.xml
Products/PloneServicesCenter/profiles/default/types.xml
Products/PloneServicesCenter/profiles/default/workflows.xml
Products/PloneServicesCenter/profiles/default/structure/.objects
