Metadata-Version: 1.0
Name: Products.PloneServicesCenter
Version: 0.2.7
Summary: A hub for information about the service options and deployments for Plone
Home-page: http://svn.plone.org/svn/collective/Products.PloneServicesCenter/trunk
Author: Alex Clark
Author-email: aclark@aclark.net
License: GPL
Platform: UNKNOWN
Classifier: Framework :: Plone
Classifier: Framework :: Zope2
Classifier: Framework :: Zope3
Classifier: Programming Language :: Python
Classifier: Topic :: Software Development :: Libraries :: Python Modules
